django_oss_storage/__init__.py
django_oss_storage/backends.py
django_oss_storage/defaults.py
ifournight_django_oss_storage-1.1.2.dist-info/LICENSE
ifournight_django_oss_storage-1.1.2.dist-info/METADATA
ifournight_django_oss_storage-1.1.2.dist-info/WHEEL
ifournight_django_oss_storage-1.1.2.dist-info/top_level.txt
ifournight_django_oss_storage-1.1.2.dist-info/RECORD
