Metadata-Version: 2.1
Name: ifournight-django-oss-storage
Version: 1.1.2
Summary: Django Aliyun OSS (Object Storage Service) storage
Home-page: https://github.com/ifournight/django-oss-storage/
Author: Song hui
Author-email: ifournight@gmail.com
License: UNKNOWN
Platform: UNKNOWN
Classifier: Development Status :: 5 - Production/Stable
Classifier: Intended Audience :: Developers
Classifier: License :: OSI Approved :: MIT License
Classifier: Operating System :: OS Independent
Classifier: Programming Language :: Python
Classifier: Programming Language :: Python :: 2
Classifier: Programming Language :: Python :: 2.6
Classifier: Programming Language :: Python :: 2.7
Classifier: Programming Language :: Python :: 3
Classifier: Programming Language :: Python :: 3.3
Classifier: Programming Language :: Python :: 3.4
Classifier: Programming Language :: Python :: 3.5
Classifier: Programming Language :: Python :: 3.6
Classifier: Framework :: Django
Requires-Dist: django (>=1.10)
Requires-Dist: oss2 (>=2.3.3)
